{"is_source_file": true, "format": "JavaScript (React)", "description": "This source file initializes and renders the root React component into the DOM, serving as the entry point for the frontend web application.", "external_files": ["react", "react-dom/client", "./index.css", "./App"], "external_methods": ["ReactDOM.createRoot", "root.render"], "published": [], "classes": [], "methods": ["ReactDOM.createRoot", "root.render"], "calls": ["ReactDOM.createRoot", "root.render"], "search-terms": ["ReactDOM", "render", "index.js", "front-end", "entry point"], "state": 2, "file_id": 6, "knowledge_revision": 20, "git_revision": "0e9bcb7e2fb64ed4dd83c2b022ed118302e8fea7", "ctags": [{"_type": "tag", "name": "root", "path": "/home/kavia/workspace/code-generation/employee-attendance-management-system-89441-89450/frontend_web_app/src/index.js", "pattern": "/^const root = ReactDOM.createRoot(document.getElementById('root'));$/", "language": "JavaScript", "kind": "constant"}], "hash": "9fc5841375336fc175b49f8767a11383", "format-version": 4, "code-base-name": "frontend_web_app", "filename": "frontend_web_app/src/index.js", "revision_history": [{"20": "0e9bcb7e2fb64ed4dd83c2b022ed118302e8fea7"}]}